macaddr.py
macaddr-2.1.dist-info/LICENSE
macaddr-2.1.dist-info/METADATA
macaddr-2.1.dist-info/WHEEL
macaddr-2.1.dist-info/top_level.txt
macaddr-2.1.dist-info/RECORD
