Metadata-Version: 2.1
Name: macaddr
Version: 2.1
Summary: Working with network MAC addresses
Home-page: UNKNOWN
Author: Jeremy Schulman
License: UNKNOWN
Platform: UNKNOWN
Classifier: Development Status :: 4 - Beta
Classifier: Intended Audience :: Developers
Classifier: Programming Language :: Python :: 3.8
Classifier: Programming Language :: Python :: 3.7
Classifier: Topic :: Software Development :: Libraries :: Python Modules
Classifier: Topic :: System :: Networking
License-File: LICENSE
